xit2md/__init__.py
xit2md-0.3.0.dist-info/METADATA
xit2md-0.3.0.dist-info/WHEEL
xit2md-0.3.0.dist-info/entry_points.txt
xit2md-0.3.0.dist-info/licenses/LICENSE
xit2md-0.3.0.dist-info/RECORD
