Metadata-Version: 2.4
Name: xit2md
Version: 0.3.0
Summary: Convert [x]it! to markdown
License-Expression: MIT
License-File: LICENSE
Author: chris48s
Requires-Python: >=3.10
Classifier: Programming Language :: Python :: 3
Classifier: Programming Language :: Python :: 3.10
Classifier: Programming Language :: Python :: 3.11
Classifier: Programming Language :: Python :: 3.12
Classifier: Programming Language :: Python :: 3.13
Classifier: Programming Language :: Python :: 3.14
Requires-Dist: stage-left (>=0.3.0,<0.4.0)
Project-URL: Home, https://github.com/chris48s/xit2md
Project-URL: Source, https://github.com/chris48s/xit2md
